{
  "Score": 0,
  "Gold": 9999195,
  "UserBulletSpawner": [
    {
      "bulletID": 1,
      "bulletCount": 3
    },
    {
      "bulletID": 2,
      "bulletCount": 1
    },
    {
      "bulletID": 3,
      "bulletCount": 1
    }
  ],
  "UserCurBullets": [
    {
      "bulletID": 1,
      "curSlotID": 1,
      "instanceID": -28270
    },
    {
      "bulletID": 1,
      "curSlotID": 2,
      "instanceID": -29280
    }
  ],
  "UserStandbyBullet": [
    {
      "BulletID": 0,
      "SlotID": 1,
      "InstanceID": 0
    },
    {
      "BulletID": 0,
      "SlotID": 2,
      "InstanceID": 0
    },
    {
      "BulletID": 0,
      "SlotID": 3,
      "InstanceID": 0
    },
    {
      "BulletID": 0,
      "SlotID": 4,
      "InstanceID": 0
    },
    {
      "BulletID": 0,
      "SlotID": 5,
      "InstanceID": 0
    }
  ],
  "UserCurBuff": null,
  "SupremeCharms": [],
  "UserMapSate": [
    {
      "CurMapID": 1,
      "MapID": 1,
      "LevelID": 1,
      "IsFinishedLevels": []
    }
  ],
  "CurRollPREveIDs": null
}